pygsti/__init__.py
pygsti/_version.py
pygsti/pgtypes.py
pygsti/algorithms/__init__.py
pygsti/algorithms/compilers.py
pygsti/algorithms/contract.py
pygsti/algorithms/core.py
pygsti/algorithms/fiducialpairreduction.py
pygsti/algorithms/fiducialselection.py
pygsti/algorithms/gaugeopt.py
pygsti/algorithms/germselection.py
pygsti/algorithms/grammatrix.py
pygsti/algorithms/grasp.py
pygsti/algorithms/mirroring.py
pygsti/algorithms/randomcircuit.py
pygsti/algorithms/rbfit.py
pygsti/algorithms/robust_phase_estimation.py
pygsti/algorithms/scoring.py
pygsti/baseobjs/__init__.py
pygsti/baseobjs/_compatibility.py
pygsti/baseobjs/advancedoptions.py
pygsti/baseobjs/basis.py
pygsti/baseobjs/basisconstructors.py
pygsti/baseobjs/errorgenbasis.py
pygsti/baseobjs/errorgenlabel.py
pygsti/baseobjs/errorgenspace.py
pygsti/baseobjs/exceptions.py
pygsti/baseobjs/label.py
pygsti/baseobjs/mongoserializable.py
pygsti/baseobjs/nicelyserializable.py
pygsti/baseobjs/outcomelabeldict.py
pygsti/baseobjs/polynomial.py
pygsti/baseobjs/profiler.py
pygsti/baseobjs/protectedarray.py
pygsti/baseobjs/qubitgraph.py
pygsti/baseobjs/resourceallocation.py
pygsti/baseobjs/smartcache.py
pygsti/baseobjs/statespace.py
pygsti/baseobjs/unitarygatefunction.py
pygsti/baseobjs/verbosityprinter.py
pygsti/baseobjs/opcalc/__init__.py
pygsti/baseobjs/opcalc/fastopcalc.cpp
pygsti/baseobjs/opcalc/fastopcalc.cpython-310-x86_64-linux-gnu.so
pygsti/baseobjs/opcalc/fastopcalc.pyx
pygsti/baseobjs/opcalc/slowopcalc.py
pygsti/circuits/__init__.py
pygsti/circuits/circuit.py
pygsti/circuits/circuitconstruction.py
pygsti/circuits/circuitlist.py
pygsti/circuits/circuitstructure.py
pygsti/circuits/cloudcircuitconstruction.py
pygsti/circuits/gstcircuits.py
pygsti/circuits/rpecircuits.py
pygsti/circuits/subcircuit_selection.py
pygsti/circuits/circuitparser/__init__.py
pygsti/circuits/circuitparser/fastcircuitparser.cpp
pygsti-0.9.14.2.dist-info/METADATA
pygsti-0.9.14.2.dist-info/WHEEL
pygsti-0.9.14.2.dist-info/top_level.txt
pygsti-0.9.14.2.dist-info/RECORD
pygsti-0.9.14.2.dist-info/licenses/LICENSE
pygsti-0.9.14.2.dist-info/licenses/NOTICE
