Metadata-Version: 2.4
Name: pygsti
Version: 0.9.14.2
Summary: A python implementation of Gate Set Tomography
Author: Erik Nielsen, Stefan Seritan, Corey Ostrove, Riley Murray, Jordan Hines, Kenneth Rudinger, Timothy Proctor, John Gamble, Robin Blume-Kohout
Author-email: pygsti@sandia.gov
Project-URL: Homepage, https://www.pygsti.info
Project-URL: Repository, https://github.com/sandialabs/pyGSTi
Project-URL: Download, https://github.com/sandialabs/pyGSTi/tarball/master
Keywords: pygsti,tomography,gate set,pigsty,pig,quantum,qubit
Classifier: Development Status :: 4 - Beta
Classifier: Intended Audience :: Science/Research
Classifier: Programming Language :: Python
Classifier: Topic :: Scientific/Engineering :: Physics
Classifier: Operating System :: Microsoft :: Windows
Classifier: Operating System :: MacOS :: MacOS X
Classifier: Operating System :: Unix
Requires-Python: >=3.9
License-File: LICENSE
License-File: NOTICE
Requires-Dist: numpy>=1.15.0
Requires-Dist: scipy
Requires-Dist: stim
Requires-Dist: plotly>=3.8.0
Requires-Dist: pandas
Requires-Dist: networkx
Requires-Dist: tqdm>=4.42.0
Provides-Extra: diamond-norm
Requires-Dist: cvxpy>=1.4.0; extra == "diamond-norm"
Provides-Extra: evolutionary-optimization
Requires-Dist: deap; extra == "evolutionary-optimization"
Provides-Extra: extensions
Requires-Dist: cython; extra == "extensions"
Provides-Extra: html-reports
Requires-Dist: jinja2; extra == "html-reports"
Requires-Dist: MarkupSafe; extra == "html-reports"
Provides-Extra: ibmq
Requires-Dist: qiskit>1; extra == "ibmq"
Requires-Dist: qiskit-ibm-runtime>=0.17.1; extra == "ibmq"
Requires-Dist: dill; extra == "ibmq"
Provides-Extra: interpygate
Requires-Dist: csaps; extra == "interpygate"
Provides-Extra: linting
Requires-Dist: autopep8; extra == "linting"
Requires-Dist: flake8; extra == "linting"
Provides-Extra: memory-profiling
Requires-Dist: psutil; extra == "memory-profiling"
Provides-Extra: mongodb
Requires-Dist: pymongo; extra == "mongodb"
Provides-Extra: msgpack
Requires-Dist: msgpack; extra == "msgpack"
Provides-Extra: multiprocessor
Requires-Dist: mpi4py; extra == "multiprocessor"
Provides-Extra: notebooks
Requires-Dist: ipython; extra == "notebooks"
Requires-Dist: notebook; extra == "notebooks"
Requires-Dist: jupyter_server; extra == "notebooks"
Provides-Extra: pytorch
Requires-Dist: torch; extra == "pytorch"
Provides-Extra: report-pdf-figures
Requires-Dist: matplotlib; extra == "report-pdf-figures"
Provides-Extra: reports
Requires-Dist: pygsti[html_reports,report_pdf_figures]; extra == "reports"
Provides-Extra: testing-no-cython-mpi
Requires-Dist: pytest; extra == "testing-no-cython-mpi"
Requires-Dist: pytest-xdist; extra == "testing-no-cython-mpi"
Requires-Dist: pytest-cov; extra == "testing-no-cython-mpi"
Requires-Dist: nbval; extra == "testing-no-cython-mpi"
Requires-Dist: packaging; extra == "testing-no-cython-mpi"
Requires-Dist: zmq; extra == "testing-no-cython-mpi"
Requires-Dist: seaborn; extra == "testing-no-cython-mpi"
Requires-Dist: ply; extra == "testing-no-cython-mpi"
Requires-Dist: cirq-core; extra == "testing-no-cython-mpi"
Requires-Dist: pygsti[diamond_norm,ibmq,interpygate,memory_profiling,msgpack,notebooks,pytorch,reports]; extra == "testing-no-cython-mpi"
Provides-Extra: testing-no-cython
Requires-Dist: pygsti[multiprocessor,testing_no_cython_mpi]; extra == "testing-no-cython"
Provides-Extra: testing
Requires-Dist: pygsti[extensions,testing_no_cython]; extra == "testing"
Provides-Extra: no-mpi
Requires-Dist: pygsti[evolutionary_optimization,extensions,linting,mongodb,testing_no_cython_mpi]; extra == "no-mpi"
Provides-Extra: complete
Requires-Dist: pygsti[multiprocessor,no_mpi]; extra == "complete"
Dynamic: license-file
